src/__init__.py
src/__main__.py
src/weather.py
melo_mcp_weather_demo-0.1.0.dist-info/METADATA
melo_mcp_weather_demo-0.1.0.dist-info/WHEEL
melo_mcp_weather_demo-0.1.0.dist-info/entry_points.txt
melo_mcp_weather_demo-0.1.0.dist-info/top_level.txt
melo_mcp_weather_demo-0.1.0.dist-info/RECORD
