Metadata-Version: 2.4
Name: melo-mcp-weather-demo
Version: 0.1.0
Summary: Add your description here
Requires-Python: >=3.12
Requires-Dist: httpx>=0.28.1
Requires-Dist: mcp[cli]>=1.12.0
